<?xml version="1.0"?>
<opencv_storage>
<stage17>
  <maxWeakCount>9</maxWeakCount>
  <stageThreshold>-9.6128249168395996e-01</stageThreshold>
  <weakClassifiers>
    <_>
      <internalNodes>
        0 -1 10141 999301836 -119479268 -1207560943 -2048351321
        2056768164 -108015581 -75314293 145242183</internalNodes>
      <leafValues>
        -5.7620817422866821e-01 5.3208774328231812e-01</leafValues></_>
    <_>
      <internalNodes>
        0 -1 8169 -285419758 483489297 -1928749129 -991213741 1320147937
        429982497 -180355143 -977411484</internalNodes>
      <leafValues>
        -4.5071443915367126e-01 4.4766274094581604e-01</leafValues></_>
    <_>
      <internalNodes>
        0 -1 2554 544183153 -360283120 -2087292669 1082188786 1968244485
        -235834464 279540229 132597129</internalNodes>
      <leafValues>
        -6.3687938451766968e-01 3.4495571255683899e-01</leafValues></_>
    <_>
      <internalNodes>
        0 -1 9269 2133320228 -10653247 -2104944813 -551872809 1122689528
        1260532874 -1617371130 -1626160316</internalNodes>
      <leafValues>
        -5.3567028045654297e-01 3.8101640343666077e-01</leafValues></_>
    <_>
      <internalNodes>
        0 -1 2295 -800418852 -1517843041 -1551688943 -523361525
        1811967181 -1998014800 1436097705 1694127518</internalNodes>
      <leafValues>
        -5.7785248756408691e-01 3.4565696120262146e-01</leafValues></_>
    <_>
      <internalNodes>
        0 -1 6428 435813295 1484761934 897317687 -1061468332 56622427
        -856281288 -1229458141 -16949250</internalNodes>
      <leafValues>
        -3.5771104693412781e-01 6.0314506292343140e-01</leafValues></_>
    <_>
      <internalNodes>
        0 -1 8210 -1877422672 319159597 -1860709283 1950377013
        -827115106 1038258132 1990132855 -1903814220</internalNodes>
      <leafValues>
        -6.2234085798263550e-01 3.7773653864860535e-01</leafValues></_>
    <_>
      <internalNodes>
        0 -1 5677 -655447997 1562001680 1233758665 -1345418233 731856047
        1809203485 1799659955 -403803391</internalNodes>
      <leafValues>
        -5.2001655101776123e-01 4.4951444864273071e-01</leafValues></_>
    <_>
      <internalNodes>
        0 -1 4155 -205576269 -1913765660 -57409 104296439 -1207887178
        -586823439 -67404465 -376608801</internalNodes>
      <leafValues>
        -4.6927797794342041e-01 5.3336799144744873e-01</leafValues></_></weakClassifiers></stage17>
</opencv_storage>
